herogold/__init__.py
herogold/colors.py
herogold/progress.py
herogold/py.typed
herogold/rainbow.py
herogold/random.py
herogold/sentinel.py
herogold/tempfile.py
herogold/argparse/__init__.py
herogold/argparse/argument.py
herogold/log/__init__.py
herogold/log/formats.py
herogold/log/handlers.py
herogold/log/logger.py
herogold/log/logger_mixin.py
herogold/log/logging.py
herogold/typing/__init__.py
herogold/typing/check.py
herogold-1.1.0.dist-info/METADATA
herogold-1.1.0.dist-info/WHEEL
herogold-1.1.0.dist-info/RECORD
