Metadata-Version: 2.4
Name: herogold
Version: 1.1.0
Summary: A single package containing personal utilities.
Project-URL: Homepage, https://github.com/HEROgold/HeroPy
Project-URL: Repository, https://github.com/HEROgold/HeroPy.git
Project-URL: Documentation, https://github.com/HEROgold/HeroPy#readme
Project-URL: Issues, https://github.com/HEROgold/HeroPy/issues
Author: HEROgold
License: MIT
Requires-Python: >=3.12
Requires-Dist: typing-extensions>=4.15.0
Provides-Extra: test
Requires-Dist: pytest>=8.3; extra == 'test'
